[{"name":"Gallery","cover":"https://i.loli.net/2020/10/05/kBcvAf7INgMLaem.jpg","date":"2023-06","description":"这里有光影流年，还有两朵穿衣裳的云，相拥在明天的河岸","url_name":"Gallery","album":[{"img_url":"https://i.loli.net/2020/10/05/qtOevHpw5XImS1J.jpg","title":"Ph.Deeeeex","describe":"Shot on Canon EOS R7"},{"img_url":"https://i.loli.net/2020/10/05/4acvniMKTx8euqp.jpg","title":"Ph.JQY","describe":"Shot on Fujifilm XT-30"},{"img_url":"https://i.loli.net/2020/10/05/4acvniMKTx8euqp.jpg","title":"Memories","describe":"金枪鱼和成绩好的合照！"}]}]